odoo/addons/hr_attendance_rfid/README.rst
odoo/addons/hr_attendance_rfid/__init__.py
odoo/addons/hr_attendance_rfid/__manifest__.py
odoo/addons/hr_attendance_rfid/data/ir_rule.xml
odoo/addons/hr_attendance_rfid/i18n/es.po
odoo/addons/hr_attendance_rfid/i18n/es_ES.po
odoo/addons/hr_attendance_rfid/i18n/fr.po
odoo/addons/hr_attendance_rfid/i18n/hr_attendance_rfid.pot
odoo/addons/hr_attendance_rfid/i18n/it.po
odoo/addons/hr_attendance_rfid/models/__init__.py
odoo/addons/hr_attendance_rfid/models/hr_employee.py
odoo/addons/hr_attendance_rfid/readme/CONFIGURE.md
odoo/addons/hr_attendance_rfid/readme/CONTRIBUTORS.md
odoo/addons/hr_attendance_rfid/readme/DESCRIPTION.md
odoo/addons/hr_attendance_rfid/readme/USAGE.md
odoo/addons/hr_attendance_rfid/security/hr_attendance_rfid.xml
odoo/addons/hr_attendance_rfid/security/ir.model.access.csv
odoo/addons/hr_attendance_rfid/static/description/icon.png
odoo/addons/hr_attendance_rfid/static/description/index.html
odoo/addons/hr_attendance_rfid/tests/__init__.py
odoo/addons/hr_attendance_rfid/tests/test_hr_attendance_rfid_process.py
odoo/addons/hr_attendance_rfid/views/hr_employee_view.xml
odoo_addon_hr_attendance_rfid-18.0.1.0.0.2.dist-info/METADATA
odoo_addon_hr_attendance_rfid-18.0.1.0.0.2.dist-info/WHEEL
odoo_addon_hr_attendance_rfid-18.0.1.0.0.2.dist-info/top_level.txt
odoo_addon_hr_attendance_rfid-18.0.1.0.0.2.dist-info/RECORD
